stilt/__init__.py
stilt/project.py
stilt-0.0.3.dist-info/LICENSE
stilt-0.0.3.dist-info/METADATA
stilt-0.0.3.dist-info/WHEEL
stilt-0.0.3.dist-info/top_level.txt
stilt-0.0.3.dist-info/RECORD
