Metadata-Version: 2.1
Name: stilt
Version: 0.0.3
Summary: Python project configreator
Home-page: https://github.com/bdube/stilt
Author: Stilt Contributors
Author-email: python.stilt@bdubeit.com
License: UNKNOWN
Platform: UNKNOWN
Classifier: Programming Language :: Python :: 3
Classifier: License :: OSI Approved :: Apache Software License
Classifier: Development Status :: 1 - Planning
